{
  "$schema": "https://json-schema.org/draft/2020-12/schema",
  "type": "object",
  "properties": {
    "name": {
      "type": "string",
      "const": "n5_varlen"
    },
    "configuration": {
      "type": "object",
      "properties": {
        "codecs": {
          "type": "array",
          "minItems": 1,
          "items": {
            "$ref": "#/$defs/codec"
          }
        }
      },
      "required": ["codecs"],
      "additionalProperties": false
    }
  },
  "required": ["name", "configuration"],
  "additionalProperties": false,
  "$defs": {
    "codec": {
      "oneOf": [
        {
          "type": "object",
          "properties": {
            "name": {
              "type": "string"
            },
            "configuration": {
              "type": "object"
            }
          },
          "required": ["name"],
          "additionalProperties": false
        },
        {
          "type": "string"
        }
      ]
    }
  }
}
