{
  "$schema": "https://json-schema.org/draft/2020-12/schema",
  "anyOf": [
    {
      "type": "object",
      "properties": {
        "name": {
          "type": "string",
          "enum": ["numcodecs.lzma"]
        },
        "configuration": {
          "type": "object",
          "properties": {
            "format": {
              "type": "integer"
            },
            "check": {
              "type": "integer"
            },
            "preset": {
              "type": "integer",
              "minimum": 0,
              "maximum": 9
            },
            "filters": {
              "type": "array",
              "items": {
                "type": "object"
              }
            }
          },
          "additionalProperties": false
        }
      },
      "required": ["name"],
      "additionalProperties": false
    },
    { "type": "string", "enum": ["numcodecs.lzma"] }
  ]
}
